pep8.py
pycodestyle.py
pycodestyle-2.4.0.dist-info/LICENSE.txt
pycodestyle-2.4.0.dist-info/METADATA
pycodestyle-2.4.0.dist-info/RECORD
pycodestyle-2.4.0.dist-info/WHEEL
pycodestyle-2.4.0.dist-info/entry_points.txt
pycodestyle-2.4.0.dist-info/namespace_packages.txt
pycodestyle-2.4.0.dist-info/top_level.txt
