Metadata-Version: 1.2
Name: pycodestyle
Version: 2.4.0
Summary: Python style guide checker
Home-page: https://pycodestyle.readthedocs.io/
Author: Johann C. Rocholl
Author-email: johann@rocholl.net
Maintainer: Ian Lee
Maintainer-email: IanLee1521@gmail.com
License: Expat license
Keywords: pycodestyle,pep8,PEP 8,PEP-8,PEP8
Platform: UNKNOWN
Classifier: Development Status :: 5 - Production/Stable
Classifier: Environment :: Console
Classifier: Intended Audience :: Developers
Classifier: License :: OSI Approved :: MIT License
Classifier: Operating System :: OS Independent
Classifier: Programming Language :: Python
Classifier: Programming Language :: Python :: 2
Classifier: Programming Language :: Python :: 2.6
Classifier: Programming Language :: Python :: 2.7
Classifier: Programming Language :: Python :: 3
Classifier: Programming Language :: Python :: 3.3
Classifier: Programming Language :: Python :: 3.4
Classifier: Programming Language :: Python :: 3.5
Classifier: Programming Language :: Python :: 3.6
Classifier: Programming Language :: Python :: Implementation :: CPython
Classifier: Programming Language :: Python :: Implementation :: PyPy
Classifier: Topic :: Software Development :: Libraries :: Python Modules
